efb_voice_recog_middleware/__init__.py
efb_voice_recog_middleware/__version__.py
efb_voice_recog_middleware/engines/__init__.py
efb_voice_recog_middleware/engines/azure.py
efb_voice_recog_middleware/engines/baidu.py
efb_voice_recog_middleware/engines/iflytek.py
efb_voice_recog_middleware/engines/tencent.py
efb_voice_recog_middleware-1.0.3.dist-info/METADATA
efb_voice_recog_middleware-1.0.3.dist-info/WHEEL
efb_voice_recog_middleware-1.0.3.dist-info/entry_points.txt
efb_voice_recog_middleware-1.0.3.dist-info/top_level.txt
efb_voice_recog_middleware-1.0.3.dist-info/RECORD
