Metadata-Version: 2.1
Name: efb-voice-recog-middleware
Version: 1.0.3
Summary: WeChat Middleware for EH Forwarder Bot to convert voice to text,                based on Baidu and Microsoft API.
Home-page: UNKNOWN
Author: catbaron
Author-email: catbaron@live.cn
License: AGPLv3+
Keywords: ehforwarderbot,EH Forwarder Bot,EH Forwarder Bot Slave Channel,wechat,weixin,chatbot
Platform: UNKNOWN
Classifier: Development Status :: 5 - Production/Stable
Classifier: License :: OSI Approved :: GNU Affero General Public License v3 or later (AGPLv3+)
Classifier: Intended Audience :: Developers
Classifier: Intended Audience :: End Users/Desktop
Classifier: Programming Language :: Python :: 3 :: Only
Classifier: Programming Language :: Python :: 3.6
Classifier: Programming Language :: Python :: 3.7
Classifier: Topic :: Communications :: Chat
Classifier: Topic :: Utilities
Requires-Python: >=3.6
Requires-Dist: ehforwarderbot (>=2.0.0b5)
Requires-Dist: PyYaml
Requires-Dist: pydub (>=0.23.1)
Requires-Dist: tencentcloud-sdk-python
Requires-Dist: websocket-client (>=0.59.0)
